mc_uuid_check/__init__.py
mc_uuid_check/__main__.py
mc_uuid_check/helperfunctions.py
mc_uuid_check/mc_offline_uuid.py
mc_uuid_check/mc_online_uuid.py
mc_uuid_check-0.0.4.dist-info/LICENSE
mc_uuid_check-0.0.4.dist-info/METADATA
mc_uuid_check-0.0.4.dist-info/WHEEL
mc_uuid_check-0.0.4.dist-info/entry_points.txt
mc_uuid_check-0.0.4.dist-info/top_level.txt
mc_uuid_check-0.0.4.dist-info/RECORD
