Metadata-Version: 2.1
Name: mc-uuid-check
Version: 0.0.4
Summary: Turns input Playername and returns Minecraft UUID's
Author-email: Faiataiga <faiataiga@protonmail.com>
License: GPL-3.0-only
Classifier: Programming Language :: Python :: 3
Classifier: Operating System :: OS Independent
Classifier: Environment :: Console
Classifier: License :: OSI Approved :: GNU General Public License v3 (GPLv3)
Classifier: Topic :: Utilities
Requires-Python: >=3.11
License-File: LICENSE
Requires-Dist: requests
